multiscale/__init__.py
multiscale/bulk_img_processing.py
multiscale/plotting.py
multiscale/tiling.py
multiscale/utility_functions.py
multiscale/itk/__init__.py
multiscale/itk/itk_plotting.py
multiscale/itk/metadata.py
multiscale/itk/multiprocess_registration_plot.py
multiscale/itk/process.py
multiscale/itk/registration.py
multiscale/itk/transform.py
multiscale/polarimetry/__init__.py
multiscale/polarimetry/analysis.py
multiscale/polarimetry/dir_dictionary.py
multiscale/polarimetry/preprocessing.py
multiscale/polarimetry/retardance.py
multiscale/polarimetry/task_scripts/__init__.py
multiscale/polarimetry/task_scripts/average_retardance.py
multiscale/polarimetry/task_scripts/curve_align_prep.py
multiscale/polarimetry/task_scripts/data_analysis.py
multiscale/polarimetry/task_scripts/data_cleaning.py
multiscale/polarimetry/task_scripts/flip_shg_indices.py
multiscale/polarimetry/task_scripts/mueller_polarization_view_registration.py
multiscale/polarimetry/task_scripts/reconstruct_images.py
multiscale/polarimetry/task_scripts/reg_to_mhr.py
multiscale/polarimetry/task_scripts/registration.py
multiscale/polarimetry/task_scripts/ssim_comparison.py
multiscale/polarimetry/task_scripts/Old tasks/__init__.py
multiscale/polarimetry/task_scripts/Old tasks/t02_multires_ps.py
multiscale/polarimetry/task_scripts/Old tasks/t03_ssim.py
multiscale/polarimetry/task_scripts/Old tasks/t04_cytospectre_prep.py
multiscale/polarimetry/task_scripts/Old tasks/t05_cytospectre_analysis.py
multiscale/toolkits/__init__.py
multiscale/toolkits/curve_align.py
multiscale/toolkits/cw_ssim.py
multiscale/toolkits/cytospectre.py
multiscale/ultrasound/__init__.py
multiscale/ultrasound/correlation.py
multiscale/ultrasound/reconstruction.py
multiscale_imaging-0.1.4.dist-info/METADATA
multiscale_imaging-0.1.4.dist-info/RECORD
multiscale_imaging-0.1.4.dist-info/WHEEL
multiscale_imaging-0.1.4.dist-info/top_level.txt
