Metadata-Version: 2.1
Name: multiscale-imaging
Version: 0.1.4
Summary: An multiscale image processing library for the Laboratory of Optical and Computational Instrumentation
Home-page: https://github.com/uw-loci/multiscale
Author: Michael Pinkert
Author-email: mpinkert@wisc.edu
License: Copyright (c) 2018, Michael Pinkert
